antraft/__init__.py
antraft/sdk.py
antraft-1.1.0.dist-info/licenses/LICENSE
antraft-1.1.0.dist-info/METADATA
antraft-1.1.0.dist-info/WHEEL
antraft-1.1.0.dist-info/top_level.txt
antraft-1.1.0.dist-info/RECORD
