Metadata-Version: 2.4
Name: antraft
Version: 1.1.0
Summary: Policy-enforced runtime for autonomous AI agents
Author: Ashraf Galib Shaik
License: MIT License
Project-URL: Homepage, https://github.com/AshrafGalibShaik/ANTRAFT
Project-URL: Bug Tracker, https://github.com/AshrafGalibShaik/ANTRAFT/issues
Classifier: Programming Language :: Python :: 3
Classifier: License :: OSI Approved :: MIT License
Classifier: Operating System :: OS Independent
Classifier: Topic :: Scientific/Engineering :: Artificial Intelligence
Classifier: Topic :: System :: Operating System
Requires-Python: >=3.10
License-File: LICENSE
Requires-Dist: typer>=0.4.0
Requires-Dist: fastapi>=0.68.0
Requires-Dist: uvicorn>=0.15.0
Requires-Dist: requests>=2.26.0
Requires-Dist: mcp>=0.1.0
Requires-Dist: pyyaml>=6.0
Requires-Dist: simpleeval>=0.9.0
Requires-Dist: httpx>=0.20.0
Dynamic: license-file
